src/__init__.py
src/alx_utils.py
tools/__init__.py
tools/checker/__init__.py
tools/checker/index.py
tools/checker/test.bash
tools/init_task/__init__.py
tools/init_task/scraper.py
alx_utils-0.8.dist-info/LICENSE
alx_utils-0.8.dist-info/METADATA
alx_utils-0.8.dist-info/WHEEL
alx_utils-0.8.dist-info/entry_points.txt
alx_utils-0.8.dist-info/top_level.txt
alx_utils-0.8.dist-info/RECORD
