Metadata-Version: 2.1
Name: alx-utils
Version: 0.8
Summary: A collection of utility tools for ALX
Home-page: https://github.com/amasin76/alx-utils
Author: BIO
License-File: LICENSE
Requires-Dist: beautifulsoup4
